opmcpg/__init__.py
opmcpg/_cpggrid.cpython-311-x86_64-linux-gnu.so
opmcpg-1.0.0.dist-info/licenses/LICENSE
thirdparty/pybind11/noxfile.py
thirdparty/pybind11/setup.py
thirdparty/pybind11/docs/benchmark.py
thirdparty/pybind11/docs/conf.py
thirdparty/pybind11/pybind11/__init__.py
thirdparty/pybind11/pybind11/__main__.py
thirdparty/pybind11/pybind11/_version.py
thirdparty/pybind11/pybind11/commands.py
thirdparty/pybind11/pybind11/py.typed
thirdparty/pybind11/pybind11/setup_helpers.py
thirdparty/pybind11/tests/conftest.py
thirdparty/pybind11/tests/env.py
thirdparty/pybind11/tests/test_async.py
thirdparty/pybind11/tests/test_buffers.py
thirdparty/pybind11/tests/test_builtin_casters.py
thirdparty/pybind11/tests/test_call_policies.py
thirdparty/pybind11/tests/test_callbacks.py
thirdparty/pybind11/tests/test_chrono.py
thirdparty/pybind11/tests/test_class.py
thirdparty/pybind11/tests/test_const_name.py
thirdparty/pybind11/tests/test_constants_and_functions.py
thirdparty/pybind11/tests/test_copy_move.py
thirdparty/pybind11/tests/test_custom_type_casters.py
thirdparty/pybind11/tests/test_custom_type_setup.py
thirdparty/pybind11/tests/test_docstring_options.py
thirdparty/pybind11/tests/test_eigen_matrix.py
thirdparty/pybind11/tests/test_eigen_tensor.py
thirdparty/pybind11/tests/test_enum.py
thirdparty/pybind11/tests/test_eval.py
thirdparty/pybind11/tests/test_eval_call.py
thirdparty/pybind11/tests/test_exceptions.py
thirdparty/pybind11/tests/test_factory_constructors.py
thirdparty/pybind11/tests/test_gil_scoped.py
thirdparty/pybind11/tests/test_iostream.py
thirdparty/pybind11/tests/test_kwargs_and_defaults.py
thirdparty/pybind11/tests/test_local_bindings.py
thirdparty/pybind11/tests/test_methods_and_attributes.py
thirdparty/pybind11/tests/test_modules.py
thirdparty/pybind11/tests/test_multiple_inheritance.py
thirdparty/pybind11/tests/test_numpy_array.py
thirdparty/pybind11/tests/test_numpy_dtypes.py
thirdparty/pybind11/tests/test_numpy_vectorize.py
thirdparty/pybind11/tests/test_opaque_types.py
opmcpg-1.0.0.dist-info/METADATA
opmcpg-1.0.0.dist-info/WHEEL
opmcpg-1.0.0.dist-info/top_level.txt
opmcpg-1.0.0.dist-info/RECORD
